setup.py
scripts/run_tkrequest.py
tkrequest/__init__.py
tkrequest/dummy_server.py
tkrequest/tkrequest.py
tkrequest/tksettings.py
tkrequest.egg-info/PKG-INFO
tkrequest.egg-info/SOURCES.txt
tkrequest.egg-info/dependency_links.txt
tkrequest.egg-info/top_level.txt
tkrequest/lib/__init__.py
tkrequest/lib/backwardcompat.py
tkrequest/lib/dump.py
tkrequest/lib/info.py
tkrequest/lib/settings.py
tkrequest/lib/tkprop.py
tkrequest/lib/__init__.py
tkrequest/lib/backwardcompat.py
tkrequest/lib/dump.py
tkrequest/lib/info.py
tkrequest/lib/settings.py
tkrequest/lib/tkprop.py