Metadata-Version: 1.1
Name: tkrequest
Version: 0.1.2
Summary: A tool for sending and receiving HTTP requests based on Tk.
Home-page: http://github.com/lishnih/tkrequest
Author: Stan
Author-email: lishnih@gmail.com
License: Public Domain
Keywords: Tk,urllib,Request
Platform: any
Classifier: Development Status :: 4 - Beta
Classifier: Intended Audience :: Developers
Classifier: License :: Public Domain
Classifier: Operating System :: OS Independent
Classifier: Programming Language :: Python
Classifier: Programming Language :: Python :: 2.7
Classifier: Programming Language :: Python :: 3.3
Classifier: Topic :: Utilities
